transfertab/__init__.py
transfertab/_nbdev.py
transfertab/extract.py
transfertab/transfer.py
transfertab/utils.py
transfertab-0.1.0.dist-info/LICENSE
transfertab-0.1.0.dist-info/METADATA
transfertab-0.1.0.dist-info/WHEEL
transfertab-0.1.0.dist-info/entry_points.txt
transfertab-0.1.0.dist-info/top_level.txt
transfertab-0.1.0.dist-info/RECORD
