Metadata-Version: 2.1
Name: transfertab
Version: 0.1.0
Summary: A library to help transfer learn for structured data.
Home-page: https://github.com/manikyabard/transfertab/tree/master/
Author: Manikya Bardhan, Joe Rishon Manoj, Ishita Datta, Rakshith R Acharya
Author-email: manikyabard@gmail.com
License: Apache Software License 2.0
Keywords: transfer learning,tabular
Platform: UNKNOWN
Classifier: Development Status :: 3 - Alpha
Classifier: Intended Audience :: Developers
Classifier: Natural Language :: English
Classifier: Programming Language :: Python :: 3.6
Classifier: Programming Language :: Python :: 3.7
Classifier: Programming Language :: Python :: 3.8
Classifier: License :: OSI Approved :: Apache Software License
Requires-Python: >=3.6
Requires-Dist: bson
Requires-Dist: fastcore
Requires-Dist: fastai
Requires-Dist: wandb
